{
	"AUTHOR" : "Federico Ghedina <federico.ghedina@gmail.com>",
	"DEMO" : {
		"MONDAINE" : {
			"TITLE" : "Leonardo MONDAINE"
		},
		"HERO" : {
			"TITLE" : "Leonardo - HERO logo"
		},
		"MALTA" : {
			"TITLE" : "Leonardo - Malta logo"
		},
		"UNDERSTAND" : {
			"TITLE" : "Leonardo - Understand"
		},
		"PLAYGROUND": {
			"TITLE": "Leonardo - Playground"
		},
		"SYNCHAZARD": {
			"TITLE": "Leonardo - Synchazard"
		}
	},
	"SERVER": {
		"PORT": "4567",
		"MSG": "server started on http://localhost:$SERVER.PORT$"
	},
	"TITLE" : "Leonardo",
	"VERSION" : 0.1
}